LICENSE
README.md
setup.py
homelink_python/__init__.py
homelink_python/cli.py
homelink_python/client.py
homelink_python/net.py
homelink_python/packet.py
homelink_python/security.py
homelinkpython.egg-info/PKG-INFO
homelinkpython.egg-info/SOURCES.txt
homelinkpython.egg-info/dependency_links.txt
homelinkpython.egg-info/entry_points.txt
homelinkpython.egg-info/requires.txt
homelinkpython.egg-info/top_level.txt