Metadata-Version: 2.1
Name: homelinkpython
Version: 1.0.1
Summary: Python Implementation of the HomeLink Client
Home-page: https://github.com/jonathanadotey77/HomeLinkPython
Author: Jonathan Adotey
Classifier: Intended Audience :: Developers
Classifier: Programming Language :: Python
Classifier: Programming Language :: Python :: 3
License-File: LICENSE
